{"$schema":"http://json-schema.org/draft-07/schema#","$comment":"https://docs.github.com/en/communities/using-templates-to-encourage-useful-issues-and-pull-requests/syntax-for-issue-forms","title":"GitHub issue forms","definitions":{"label":{"type":"string","minLength":1},"description":{"type":"string"},"id":{"type":"string","minLength":1},"placeholder":{"type":"string"},"value":{"type":"string"},"render":{"type":"string"},"type":{"type":"string","enum":["checkboxes","dropdown","input","markdown","textarea"]},"validations":{"type":"object","additionalProperties":false,"properties":{"required":{"type":"boolean","default":false}}},"body":{"type":"object","required":["type"],"properties":{"type":{"$ref":"#/definitions/type"}},"allOf":[{"if":{"properties":{"type":{"const":"markdown"}}},"then":{"required":["type","attributes"],"type":"object","additionalProperties":false,"$comment":"For additionalProperties to work 'type' must also be present here.","properties":{"type":{"$ref":"#/definitions/type"},"attributes":{"type":"object","additionalProperties":false,"required":["value"],"properties":{"value":{"type":"string","minLength":1}}}}}},{"if":{"properties":{"type":{"const":"textarea"}}},"then":{"required":["type","attributes"],"type":"object","additionalProperties":false,"$comment":"For additionalProperties to work 'type' must also be present here.","properties":{"type":{"$ref":"#/definitions/type"},"attributes":{"type":"object","additionalProperties":false,"required":["label"],"properties":{"label":{"$ref":"#/definitions/label"},"description":{"$ref":"#/definitions/description"},"placeholder":{"$ref":"#/definitions/placeholder"},"value":{"$ref":"#/definitions/value"},"render":{"$ref":"#/definitions/render"}}},"id":{"$ref":"#/definitions/id"},"validations":{"$ref":"#/definitions/validations"}}}},{"if":{"properties":{"type":{"const":"input"}}},"then":{"required":["type","attributes"],"type":"object","additionalProperties":false,"$comment":"For additionalProperties to work 'type' must also be present here.","properties":{"type":{"$ref":"#/definitions/type"},"attributes":{"type":"object","additionalProperties":false,"required":["label"],"properties":{"label":{"$ref":"#/definitions/label"},"description":{"$ref":"#/definitions/description"},"placeholder":{"$ref":"#/definitions/placeholder"},"value":{"$ref":"#/definitions/value"}}},"id":{"$ref":"#/definitions/id"},"validations":{"$ref":"#/definitions/validations"}}}},{"if":{"properties":{"type":{"const":"dropdown"}}},"then":{"required":["type","attributes"],"type":"object","additionalProperties":false,"$comment":"For additionalProperties to work 'type' must also be present here.","properties":{"type":{"$ref":"#/definitions/type"},"attributes":{"type":"object","additionalProperties":false,"required":["label","options"],"properties":{"label":{"$ref":"#/definitions/label"},"description":{"$ref":"#/definitions/description"},"multiple":{"type":"boolean"},"options":{"type":"array","minItems":1,"uniqueItems":true,"items":{"type":"string","minLength":1}}}},"id":{"$ref":"#/definitions/id"},"validations":{"$ref":"#/definitions/validations"}}}},{"if":{"properties":{"type":{"const":"checkboxes"}}},"then":{"required":["type","attributes"],"type":"object","additionalProperties":false,"$comment":"For additionalProperties to work 'type' must also be present here.","properties":{"type":{"$ref":"#/definitions/type"},"attributes":{"type":"object","additionalProperties":false,"required":["label","options"],"properties":{"label":{"$ref":"#/definitions/label"},"description":{"$ref":"#/definitions/description"},"options":{"type":"array","minItems":1,"uniqueItems":true,"items":{"type":"object","additionalProperties":false,"required":["label"],"properties":{"label":{"type":"string","minLength":1},"required":{"type":"boolean","default":false}}}}}},"id":{"$ref":"#/definitions/id"}}}}]}},"type":"object","additionalProperties":false,"required":["name","description"],"properties":{"name":{"type":"string","minLength":1},"description":{"type":"string","minLength":1},"assignees":{"oneOf":[{"type":"string","minLength":1},{"type":"array","minItems":1,"uniqueItems":true,"items":{"type":"string","minLength":1}}]},"labels":{"type":"array","minItems":1,"uniqueItems":true,"items":{"type":"string","minLength":1}},"title":{"type":"string","minLength":1},"body":{"type":"array","minItems":1,"items":{"$ref":"#/definitions/body"}}}}