{"$schema":"http://json-schema.org/draft-07/schema#","$comment":"https://minecraft.fandom.com/wiki/Custom_dimension#Dimension_type","title":"Minecraft Data Pack Dimension Type","type":"object","properties":{"name":{"title":"Name","type":"string"},"ultrawarm":{"title":"Ultrawarm","type":"boolean"},"natural":{"title":"Natural","type":"boolean"},"coordinate_scale":{"title":"Coordinate Scale","type":"number"},"has_skylight":{"title":"Has Skylight","type":"boolean"},"has_ceiling":{"title":"Has Ceiling","type":"boolean"},"ambient_light":{"title":"Ambient Light","type":"number","default":0.5},"fixed_time":{"title":"Fixed Time","anyOf":[{"type":"boolean","default":false},{"type":"integer","minimum":0,"maximum":24000}]},"piglin_safe":{"title":"Piglin Safe","type":"boolean"},"bed_works":{"title":"Bed Words","type":"boolean"},"respawn_anchor_works":{"title":"Respawn Anchor Works","type":"boolean"},"has_raids":{"title":"Has Raids","type":"boolean"},"logical_height":{"title":"Logical Height","type":"integer"},"min_y":{"title":"Minimum Y","type":"integer","minimum":-2032,"maximum":2031,"multipleOf":16},"height":{"title":"Height","type":"integer","minimum":0,"maximum":4096,"multipleOf":16},"infiniburn":{"title":"Infiniburn","type":"string"},"effects":{"title":"Effects","type":"string","enum":["minecraft:overworld","minecraft:the_nether","minecraft:the_end"],"default":"minecraft:overworld"}}}